CHANGES.rst
LICENSE
MANIFEST.in
README.rst
setup.cfg
setup.py
pyramid_kvs/__init__.py
pyramid_kvs/cache.py
pyramid_kvs/kvs.py
pyramid_kvs/perlsess.py
pyramid_kvs/ratelimit.py
pyramid_kvs/serializer.py
pyramid_kvs/session.py
pyramid_kvs/storable.py
pyramid_kvs/testing.py
pyramid_kvs.egg-info/PKG-INFO
pyramid_kvs.egg-info/SOURCES.txt
pyramid_kvs.egg-info/dependency_links.txt
pyramid_kvs.egg-info/not-zip-safe
pyramid_kvs.egg-info/requires.txt
pyramid_kvs.egg-info/top_level.txt
pyramid_kvs/tests/__init__.py
pyramid_kvs/tests/compat.py
pyramid_kvs/tests/conftest.py
pyramid_kvs/tests/test_cache.py
pyramid_kvs/tests/test_ratelimit.py
pyramid_kvs/tests/test_session.py