Metadata-Version: 2.1
Name: pyramid-kvs
Version: 1.0.0
Summary: Session and cache for Pyramid
Home-page: https://github.com/Gandi/pyramid_kvs
Author: Gandi
Author-email: feedback@gandi.net
License: UNKNOWN
Keywords: web pyramid pylons
Platform: UNKNOWN
Classifier: Programming Language :: Python
Classifier: Framework :: Pyramid
Classifier: Topic :: Internet :: WWW/HTTP
Classifier: Topic :: Internet :: WWW/HTTP :: WSGI
Classifier: License :: OSI Approved :: GNU General Public License v2 (GPLv2)
Provides-Extra: test
Provides-Extra: dev
License-File: LICENSE
